basicagi/__init__.py
basicagi/basic_agi.py
basicagi-1.0.1.dist-info/licenses/LICENSE
basicagi-1.0.1.dist-info/METADATA
basicagi-1.0.1.dist-info/WHEEL
basicagi-1.0.1.dist-info/top_level.txt
basicagi-1.0.1.dist-info/RECORD
