Metadata-Version: 2.4
Name: basicagi
Version: 1.0.1
Summary: A Python library for Asterisk Gateway Interface (AGI) applications
Home-page: https://github.com/andrius/asterisk-basicagi
Author: Andrius Kairiukstis
Author-email: Andrius Kairiukstis <k@andrius.mobi>
License: MIT
Project-URL: Homepage, https://github.com/andrius/asterisk-basicagi
Project-URL: Repository, https://github.com/andrius/asterisk-basicagi
Project-URL: Documentation, https://github.com/andrius/asterisk-basicagi/blob/main/README.md
Project-URL: Bug Reports, https://github.com/andrius/asterisk-basicagi/issues
Keywords: asterisk,agi,pbx,telephony,voip
Classifier: Development Status :: 5 - Production/Stable
Classifier: Intended Audience :: Developers
Classifier: Intended Audience :: Telecommunications Industry
Classifier: Topic :: Communications :: Internet Phone
Classifier: Topic :: Communications :: Telephony
Classifier: Topic :: Software Development :: Libraries :: Python Modules
Classifier: License :: OSI Approved :: MIT License
Classifier: Programming Language :: Python :: 3
Classifier: Programming Language :: Python :: 3.7
Classifier: Programming Language :: Python :: 3.8
Classifier: Programming Language :: Python :: 3.9
Classifier: Programming Language :: Python :: 3.10
Classifier: Programming Language :: Python :: 3.11
Classifier: Programming Language :: Python :: 3.12
Classifier: Programming Language :: Python :: 3.13
Classifier: Operating System :: OS Independent
Requires-Python: >=3.7
License-File: LICENSE
Dynamic: author
Dynamic: home-page
Dynamic: license-file
Dynamic: requires-python
